edapi/__init__.py
edapi/constants.py
edapi/edapi.py
edapi/utils.py
edapi/models/__.init__.py
edapi/models/course.py
edapi/models/thread.py
edapi/models/user.py
edapi/types/__init__.py
edapi/types/types.py
edapi/types/api_types/__init__.py
edapi/types/api_types/category.py
edapi/types/api_types/content.py
edapi/types/api_types/course.py
edapi/types/api_types/thread.py
edapi/types/api_types/user.py
edapi/types/api_types/endpoints/__init__.py
edapi/types/api_types/endpoints/activity.py
edapi/types/api_types/endpoints/analytics.py
edapi/types/api_types/endpoints/files.py
edapi/types/api_types/endpoints/threads.py
edapi/types/api_types/endpoints/user.py
edapi_fork-0.1.5.dist-info/licenses/LICENSE
edapi_fork-0.1.5.dist-info/METADATA
edapi_fork-0.1.5.dist-info/WHEEL
edapi_fork-0.1.5.dist-info/top_level.txt
edapi_fork-0.1.5.dist-info/RECORD
