Metadata-Version: 2.4
Name: edapi-fork
Version: 0.1.5
Summary: An unofficial integration of the Ed API with Python
Project-URL: Homepage, https://github.com/cooi123/edapi
Classifier: License :: OSI Approved :: GNU General Public License v3 (GPLv3)
Requires-Python: >=3.9
License-File: LICENSE
Requires-Dist: requests
Requires-Dist: beautifulsoup4
Requires-Dist: pydantic>=2.10.6
Provides-Extra: dev
Requires-Dist: python-dotenv; extra == "dev"
Requires-Dist: pandas>=2.2.3; extra == "dev"
Provides-Extra: build
Requires-Dist: build>=1.2.2.post1; extra == "build"
Requires-Dist: twine>=6.1.0; extra == "build"
Dynamic: license-file
